rtl/uart_rx.v
`timescale 1ns/1ps

module uart_rx #
(
    parameter CLKS_PER_BIT = 8
)
(
    input clk,
    input rst,
    input rx,
    output reg [7:0] data_out,
    output reg rx_valid
);

    localparam IDLE = 3'd0;
    localparam START_BIT = 3'd1;
    localparam DATA_BITS = 3'd2;
    localparam STOP_BIT = 3'd3;

    reg [2:0] state;
    reg [2:0] bit_index;
    reg [15:0] clk_count;

    always @(posedge clk or posedge rst) begin
        if (rst) begin
            state <= IDLE;
            rx_valid  <= 0;
            clk_count <= 0;
            bit_index <= 0;
        end
        else begin
            rx_valid <= 0;

            case (state)

            IDLE: begin
                if (rx == 0) begin
                    state <= START_BIT;
                    clk_count <= 0;
                end
            end

            START_BIT: begin
                if (clk_count == (CLKS_PER_BIT/2)) begin
                    if (rx == 0) begin
                        clk_count <= 0;
                        state <= DATA_BITS;
                    end
                    else
                        state <= IDLE;
                end
                else
                    clk_count <= clk_count + 1;
            end

            DATA_BITS: begin
                if (clk_count < CLKS_PER_BIT-1)
                    clk_count <= clk_count + 1;
                else begin
                    clk_count <= 0;
                    data_out[bit_index] <= rx;

                    if (bit_index < 7)
                        bit_index <= bit_index + 1;
                    else begin
                        bit_index <= 0;
                        state <= STOP_BIT;
                    end
                end
            end

            STOP_BIT: begin
                if (clk_count < CLKS_PER_BIT-1)
                    clk_count <= clk_count + 1;
                else begin
                    rx_valid <= 1;
                    state <= IDLE;
                    clk_count <= 0;
                end
            end

            endcase
        end
    end

endmodule

rtl/uart_tx.v
`timescale 1ns/1ps

module uart_tx #
(
    parameter CLKS_PER_BIT = 8
)
(
    input        clk,
    input        rst,
    input        start,
    input  [7:0] data_in,
    output reg   tx,
    output reg   busy
);

    localparam IDLE      = 3'd0;
    localparam START_BIT = 3'd1;
    localparam DATA_BITS = 3'd2;
    localparam STOP_BIT  = 3'd3;

    reg [2:0] state;
    reg [2:0] bit_index;
    reg [15:0] clk_count;
    reg [7:0] data_reg;

    always @(posedge clk or posedge rst) begin
        if (rst) begin
            state     <= IDLE;
            tx        <= 1'b1;
            busy      <= 1'b0;
            clk_count <= 0;
            bit_index <= 0;
        end
        else begin
            case (state)

            IDLE: begin
                tx   <= 1'b1;
                busy <= 1'b0;
                clk_count <= 0;
                bit_index <= 0;

                if (start) begin
                    busy     <= 1'b1;
                    data_reg <= data_in;
                    state    <= START_BIT;
                end
            end

            START_BIT: begin
                tx <= 1'b0;
                if (clk_count < CLKS_PER_BIT-1)
                    clk_count <= clk_count + 1;
                else begin
                    clk_count <= 0;
                    state <= DATA_BITS;
                end
            end

            DATA_BITS: begin
                tx <= data_reg[bit_index];

                if (clk_count < CLKS_PER_BIT-1)
                    clk_count <= clk_count + 1;
                else begin
                    clk_count <= 0;
                    if (bit_index < 7)
                        bit_index <= bit_index + 1;
                    else begin
                        bit_index <= 0;
                        state <= STOP_BIT;
                    end
                end
            end

            STOP_BIT: begin
                tx <= 1'b1;
                if (clk_count < CLKS_PER_BIT-1)
                    clk_count <= clk_count + 1;
                else begin
                    state <= IDLE;
                    clk_count <= 0;
                end
            end

            endcase
        end
    end

endmodule

rtl/uart_top.v
`timescale 1ns/1ps

module uart_top
(
    input clk,
    input rst,
    input start,
    input [7:0] data_in,
    output [7:0] rx_data,
    output rx_valid,
    output tx
);

    wire tx_line;

    uart_tx #(.CLKS_PER_BIT(8)) TX (
        .clk(clk),
        .rst(rst),
        .start(start),
        .data_in(data_in),
        .tx(tx_line),
        .busy()
    );

    uart_rx #(.CLKS_PER_BIT(8)) RX (
        .clk(clk),
        .rst(rst),
        .rx(tx_line),
        .data_out(rx_data),
        .rx_valid(rx_valid)
    );

    assign tx = tx_line;

endmodule

tb/tb_uart.v
`timescale 1ns/1ps

module tb_uart;

    reg clk;
    reg rst;
    reg start;
    reg [7:0] data_in;
    wire [7:0] rx_data;   // will be driven by dut
    wire rx_valid;        // will be driven by dut
    wire tx;              // will be driven by dut

    uart_top dut (
        .clk(clk),
        .rst(rst),
        .start(start),
        .data_in(data_in),
        .rx_data(rx_data),
        .rx_valid(rx_valid),
        .tx(tx)
    );

    initial begin
    	$dumpfile("uart_tb.vcd");   // VCD output file
    	$dumpvars(0, tb_uart);      // dump all signals in tb_uart hierarchy
    end
    // 100MHz clock
    initial clk = 0;
    always #5 clk = ~clk;

    // expected signals
    reg [7:0] expected_tx [0:3];
    reg [7:0] expected_rx [0:3];

    integer tx_count = 0;
    integer rx_count = 0;
    integer pass = 0;
    integer fail = 0;
    integer i;
    
    // Task to send a byte
    task send_byte;
        input [7:0] data;
        begin
            @(posedge clk);
            data_in <= data;
            start <= 1;
            expected_tx[tx_count] = data;
            tx_count = tx_count + 1;

            @(posedge clk);
            start <= 0;

            @(posedge rx_valid);
            expected_rx[rx_count] = rx_data;
            rx_count = rx_count + 1;
        end
    endtask

    initial begin
        rst = 1;
        start = 0;
        data_in = 0;

        repeat (5) @(posedge clk);
        rst = 0;

        send_byte(8'hA5);
        send_byte(8'h3C);
        send_byte(8'hF0);
        send_byte(8'h55);

        #20;

        $display("\n==== SCOREBOARD ====");

        for (i = 0; i < tx_count; i = i + 1) begin
            if (expected_tx[i] == expected_rx[i]) begin
                pass = pass + 1;
                $display("PASS Byte %0d : %h", i, expected_rx[i]);
            end
            else begin
                fail = fail + 1;
                $display("FAIL Byte %0d : TX=%h RX=%h",
                         i, expected_tx[i], expected_rx[i]);
            end
        end

        $display("TOTAL PASS = %0d", pass);
        $display("TOTAL FAIL = %0d", fail);

        $finish;
    end

endmodule

uart_tb.vcd
$date
	Thu Mar  5 19:10:47 2026
$end
$version
	ModelSim Version 10.5b
$end
$timescale
	1ps
$end

$scope module tb_uart $end
$var reg 1 ! clk $end
$var reg 1 " rst $end
$var reg 1 # start $end
$var reg 8 $ data_in [7:0] $end
$var wire 1 % rx_data [7] $end
$var wire 1 & rx_data [6] $end
$var wire 1 ' rx_data [5] $end
$var wire 1 ( rx_data [4] $end
$var wire 1 ) rx_data [3] $end
$var wire 1 * rx_data [2] $end
$var wire 1 + rx_data [1] $end
$var wire 1 , rx_data [0] $end
$var wire 1 - rx_valid $end
$var wire 1 . tx $end
$var integer 32 / tx_count $end
$var integer 32 0 rx_count $end
$var integer 32 1 pass $end
$var integer 32 2 fail $end
$var integer 32 3 i $end

$scope task send_byte $end
$var reg 8 4 data [7:0] $end
$upscope $end

$scope module dut $end
$var wire 1 5 clk $end
$var wire 1 6 rst $end
$var wire 1 7 start $end
$var wire 1 8 data_in [7] $end
$var wire 1 9 data_in [6] $end
$var wire 1 : data_in [5] $end
$var wire 1 ; data_in [4] $end
$var wire 1 < data_in [3] $end
$var wire 1 = data_in [2] $end
$var wire 1 > data_in [1] $end
$var wire 1 ? data_in [0] $end
$var wire 1 % rx_data [7] $end
$var wire 1 & rx_data [6] $end
$var wire 1 ' rx_data [5] $end
$var wire 1 ( rx_data [4] $end
$var wire 1 ) rx_data [3] $end
$var wire 1 * rx_data [2] $end
$var wire 1 + rx_data [1] $end
$var wire 1 , rx_data [0] $end
$var wire 1 - rx_valid $end
$var wire 1 . tx $end
$var wire 1 @ tx_line $end

$scope module TX $end
$var parameter 32 A CLKS_PER_BIT $end
$var parameter 3 B IDLE $end
$var parameter 3 C START_BIT $end
$var parameter 3 D DATA_BITS $end
$var parameter 3 E STOP_BIT $end
$var wire 1 5 clk $end
$var wire 1 6 rst $end
$var wire 1 7 start $end
$var wire 1 8 data_in [7] $end
$var wire 1 9 data_in [6] $end
$var wire 1 : data_in [5] $end
$var wire 1 ; data_in [4] $end
$var wire 1 < data_in [3] $end
$var wire 1 = data_in [2] $end
$var wire 1 > data_in [1] $end
$var wire 1 ? data_in [0] $end
$var reg 1 F tx $end
$var reg 1 G busy $end
$var reg 3 H state [2:0] $end
$var reg 3 I bit_index [2:0] $end
$var reg 16 J clk_count [15:0] $end
$var reg 8 K data_reg [7:0] $end
$upscope $end

$scope module RX $end
$var parameter 32 L CLKS_PER_BIT $end
$var parameter 3 M IDLE $end
$var parameter 3 N START_BIT $end
$var parameter 3 O DATA_BITS $end
$var parameter 3 P STOP_BIT $end
$var wire 1 5 clk $end
$var wire 1 6 rst $end
$var wire 1 @ rx $end
$var reg 8 Q data_out [7:0] $end
$var reg 1 R rx_valid $end
$var reg 3 S state [2:0] $end
$var reg 3 T bit_index [2:0] $end
$var reg 16 U clk_count [15:0] $end
$upscope $end
$upscope $end
$upscope $end
$enddefinitions $end
#0
$dumpvars
0!
1"
0#
b0 $
1F
0G
b0 H
b0 I
b0 J
bx K
bx Q
0R
b0 S
b0 T
b0 U
bx 4
b1000 A
b0 B
b1 C
b10 D
b11 E
b1000 L
b0 M
b1 N
b10 O
b11 P
b0 /
b0 0
b0 1
b0 2
bx 3
x,
x+
x*
x)
x(
x'
x&
x%
0-
1.
1@
0?
0>
0=
0<
0;
0:
09
08
07
16
05
$end
#5000
1!
15
#10000
0!
05
#15000
1!
15
#20000
0!
05
#25000
1!
15
#30000
0!
05
#35000
1!
15
#40000
0!
05
#45000
1!
15
0"
b10100101 4
06
#50000
0!
05
#55000
1!
15
b1 /
b10100101 $
1#
1?
1=
1:
18
17
#60000
0!
05
#65000
1!
15
1G
b10100101 K
b1 H
0#
07
#70000
0!
05
#75000
1!
15
0F
b1 J
0@
0.
#80000
0!
05
#85000
1!
15
b10 J
b1 S
#90000
0!
05
#95000
1!
15
b11 J
b1 U
#100000
0!
05
#105000
1!
15
b100 J
b10 U
#110000
0!
05
#115000
1!
15
b101 J
b11 U
#120000
0!
05
#125000
1!
15
b110 J
b100 U
#130000
0!
05
#135000
1!
15
b111 J
b0 U
b10 S
#140000
0!
05
#145000
1!
15
b0 J
b10 H
b1 U
#150000
0!
05
#155000
1!
15
1F
b1 J
b10 U
1@
1.
#160000
0!
05
#165000
1!
15
b10 J
b11 U
#170000
0!
05
#175000
1!
15
b11 J
b100 U
#180000
0!
05
#185000
1!
15
b100 J
b101 U
#190000
0!
05
#195000
1!
15
b101 J
b110 U
#200000
0!
05
#205000
1!
15
b110 J
b111 U
#210000
0!
05
#215000
1!
15
b111 J
b0 U
bx1 Q
b1 T
1,
#220000
0!
05
#225000
1!
15
b0 J
b1 I
b1 U
#230000
0!
05
#235000
1!
15
0F
b1 J
b10 U
0@
0.
#240000
0!
05
#245000
1!
15
b10 J
b11 U
#250000
0!
05
#255000
1!
15
b11 J
b100 U
#260000
0!
05
#265000
1!
15
b100 J
b101 U
#270000
0!
05
#275000
1!
15
b101 J
b110 U
#280000
0!
05
#285000
1!
15
b110 J
b111 U
#290000
0!
05
#295000
1!
15
b111 J
b0 U
bx01 Q
b10 T
0+
#300000
0!
05
#305000
1!
15
b0 J
b10 I
b1 U
#310000
0!
05
#315000
1!
15
1F
b1 J
b10 U
1@
1.
#320000
0!
05
#325000
1!
15
b10 J
b11 U
#330000
0!
05
#335000
1!
15
b11 J
b100 U
#340000
0!
05
#345000
1!
15
b100 J
b101 U
#350000
0!
05
#355000
1!
15
b101 J
b110 U
#360000
0!
05
#365000
1!
15
b110 J
b111 U
#370000
0!
05
#375000
1!
15
b111 J
b0 U
bx101 Q
b11 T
1*
#380000
0!
05
#385000
1!
15
b0 J
b11 I
b1 U
#390000
0!
05
#395000
1!
15
0F
b1 J
b10 U
0@
0.
#400000
0!
05
#405000
1!
15
b10 J
b11 U
#410000
0!
05
#415000
1!
15
b11 J
b100 U
#420000
0!
05
#425000
1!
15
b100 J
b101 U
#430000
0!
05
#435000
1!
15
b101 J
b110 U
#440000
0!
05
#445000
1!
15
b110 J
b111 U
#450000
0!
05
#455000
1!
15
b111 J
b0 U
bx0101 Q
b100 T
0)
#460000
0!
05
#465000
1!
15
b0 J
b100 I
b1 U
#470000
0!
05
#475000
1!
15
b1 J
b10 U
#480000
0!
05
#485000
1!
15
b10 J
b11 U
#490000
0!
05
#495000
1!
15
b11 J
b100 U
#500000
0!
05
#505000
1!
15
b100 J
b101 U
#510000
0!
05
#515000
1!
15
b101 J
b110 U
#520000
0!
05
#525000
1!
15
b110 J
b111 U
#530000
0!
05
#535000
1!
15
b111 J
b0 U
bx00101 Q
b101 T
0(
#540000
0!
05
#545000
1!
15
b0 J
b101 I
b1 U
#550000
0!
05
#555000
1!
15
1F
b1 J
b10 U
1@
1.
#560000
0!
05
#565000
1!
15
b10 J
b11 U
#570000
0!
05
#575000
1!
15
b11 J
b100 U
#580000
0!
05
#585000
1!
15
b100 J
b101 U
#590000
0!
05
#595000
1!
15
b101 J
b110 U
#600000
0!
05
#605000
1!
15
b110 J
b111 U
#610000
0!
05
#615000
1!
15
b111 J
b0 U
bx100101 Q
b110 T
1'
#620000
0!
05
#625000
1!
15
b0 J
b110 I
b1 U
#630000
0!
05
#635000
1!
15
0F
b1 J
b10 U
0@
0.
#640000
0!
05
#645000
1!
15
b10 J
b11 U
#650000
0!
05
#655000
1!
15
b11 J
b100 U
#660000
0!
05
#665000
1!
15
b100 J
b101 U
#670000
0!
05
#675000
1!
15
b101 J
b110 U
#680000
0!
05
#685000
1!
15
b110 J
b111 U
#690000
0!
05
#695000
1!
15
b111 J
b0 U
bx0100101 Q
b111 T
0&
#700000
0!
05
#705000
1!
15
b0 J
b111 I
b1 U
#710000
0!
05
#715000
1!
15
1F
b1 J
b10 U
1@
1.
#720000
0!
05
#725000
1!
15
b10 J
b11 U
#730000
0!
05
#735000
1!
15
b11 J
b100 U
#740000
0!
05
#745000
1!
15
b100 J
b101 U
#750000
0!
05
#755000
1!
15
b101 J
b110 U
#760000
0!
05
#765000
1!
15
b110 J
b111 U
#770000
0!
05
#775000
1!
15
b111 J
b0 U
b10100101 Q
b0 T
b11 S
1%
#780000
0!
05
#785000
1!
15
b0 J
b0 I
b11 H
b1 U
#790000
0!
05
#795000
1!
15
b1 J
b10 U
#800000
0!
05
#805000
1!
15
b10 J
b11 U
#810000
0!
05
#815000
1!
15
b11 J
b100 U
#820000
0!
05
#825000
1!
15
b100 J
b101 U
#830000
0!
05
#835000
1!
15
b101 J
b110 U
#840000
0!
05
#845000
1!
15
b110 J
b111 U
#850000
0!
05
#855000
1!
15
b111 J
1R
b0 S
b0 U
1-
b1 0
b111100 4
#860000
0!
05
#865000
1!
15
b10 /
b0 H
b0 J
0R
b111100 $
1#
0?
1<
1;
08
17
0-
#870000
0!
05
#875000
1!
15
0G
1G
b111100 K
b1 H
0#
07
#880000
0!
05
#885000
1!
15
0F
b1 J
0@
0.
#890000
0!
05
#895000
1!
15
b10 J
b1 S
#900000
0!
05
#905000
1!
15
b11 J
b1 U
#910000
0!
05
#915000
1!
15
b100 J
b10 U
#920000
0!
05
#925000
1!
15
b101 J
b11 U
#930000
0!
05
#935000
1!
15
b110 J
b100 U
#940000
0!
05
#945000
1!
15
b111 J
b0 U
b10 S
#950000
0!
05
#955000
1!
15
b0 J
b10 H
b1 U
#960000
0!
05
#965000
1!
15
b1 J
b10 U
#970000
0!
05
#975000
1!
15
b10 J
b11 U
#980000
0!
05
#985000
1!
15
b11 J
b100 U
#990000
0!
05
#995000
1!
15
b100 J
b101 U
#1000000
0!
05
#1005000
1!
15
b101 J
b110 U
#1010000
0!
05
#1015000
1!
15
b110 J
b111 U
#1020000
0!
05
#1025000
1!
15
b111 J
b0 U
b10100100 Q
b1 T
0,
#1030000
0!
05
#1035000
1!
15
b0 J
b1 I
b1 U
#1040000
0!
05
#1045000
1!
15
b1 J
b10 U
#1050000
0!
05
#1055000
1!
15
b10 J
b11 U
#1060000
0!
05
#1065000
1!
15
b11 J
b100 U
#1070000
0!
05
#1075000
1!
15
b100 J
b101 U
#1080000
0!
05
#1085000
1!
15
b101 J
b110 U
#1090000
0!
05
#1095000
1!
15
b110 J
b111 U
#1100000
0!
05
#1105000
1!
15
b111 J
b0 U
b10 T
#1110000
0!
05
#1115000
1!
15
b0 J
b10 I
b1 U
#1120000
0!
05
#1125000
1!
15
1F
b1 J
b10 U
1@
1.
#1130000
0!
05
#1135000
1!
15
b10 J
b11 U
#1140000
0!
05
#1145000
1!
15
b11 J
b100 U
#1150000
0!
05
#1155000
1!
15
b100 J
b101 U
#1160000
0!
05
#1165000
1!
15
b101 J
b110 U
#1170000
0!
05
#1175000
1!
15
b110 J
b111 U
#1180000
0!
05
#1185000
1!
15
b111 J
b0 U
b11 T
#1190000
0!
05
#1195000
1!
15
b0 J
b11 I
b1 U
#1200000
0!
05
#1205000
1!
15
b1 J
b10 U
#1210000
0!
05
#1215000
1!
15
b10 J
b11 U
#1220000
0!
05
#1225000
1!
15
b11 J
b100 U
#1230000
0!
05
#1235000
1!
15
b100 J
b101 U
#1240000
0!
05
#1245000
1!
15
b101 J
b110 U
#1250000
0!
05
#1255000
1!
15
b110 J
b111 U
#1260000
0!
05
#1265000
1!
15
b111 J
b0 U
b10101100 Q
b100 T
1)
#1270000
0!
05
#1275000
1!
15
b0 J
b100 I
b1 U
#1280000
0!
05
#1285000
1!
15
b1 J
b10 U
#1290000
0!
05
#1295000
1!
15
b10 J
b11 U
#1300000
0!
05
#1305000
1!
15
b11 J
b100 U
#1310000
0!
05
#1315000
1!
15
b100 J
b101 U
#1320000
0!
05
#1325000
1!
15
b101 J
b110 U
#1330000
0!
05
#1335000
1!
15
b110 J
b111 U
#1340000
0!
05
#1345000
1!
15
b111 J
b0 U
b10111100 Q
b101 T
1(
#1350000
0!
05
#1355000
1!
15
b0 J
b101 I
b1 U
#1360000
0!
05
#1365000
1!
15
b1 J
b10 U
#1370000
0!
05
#1375000
1!
15
b10 J
b11 U
#1380000
0!
05
#1385000
1!
15
b11 J
b100 U
#1390000
0!
05
#1395000
1!
15
b100 J
b101 U
#1400000
0!
05
#1405000
1!
15
b101 J
b110 U
#1410000
0!
05
#1415000
1!
15
b110 J
b111 U
#1420000
0!
05
#1425000
1!
15
b111 J
b0 U
b110 T
#1430000
0!
05
#1435000
1!
15
b0 J
b110 I
b1 U
#1440000
0!
05
#1445000
1!
15
0F
b1 J
b10 U
0@
0.
#1450000
0!
05
#1455000
1!
15
b10 J
b11 U
#1460000
0!
05
#1465000
1!
15
b11 J
b100 U
#1470000
0!
05
#1475000
1!
15
b100 J
b101 U
#1480000
0!
05
#1485000
1!
15
b101 J
b110 U
#1490000
0!
05
#1495000
1!
15
b110 J
b111 U
#1500000
0!
05
#1505000
1!
15
b111 J
b0 U
b111 T
#1510000
0!
05
#1515000
1!
15
b0 J
b111 I
b1 U
#1520000
0!
05
#1525000
1!
15
b1 J
b10 U
#1530000
0!
05
#1535000
1!
15
b10 J
b11 U
#1540000
0!
05
#1545000
1!
15
b11 J
b100 U
#1550000
0!
05
#1555000
1!
15
b100 J
b101 U
#1560000
0!
05
#1565000
1!
15
b101 J
b110 U
#1570000
0!
05
#1575000
1!
15
b110 J
b111 U
#1580000
0!
05
#1585000
1!
15
b111 J
b0 U
b111100 Q
b0 T
b11 S
0%
#1590000
0!
05
#1595000
1!
15
b0 J
b0 I
b11 H
b1 U
#1600000
0!
05
#1605000
1!
15
1F
b1 J
b10 U
1@
1.
#1610000
0!
05
#1615000
1!
15
b10 J
b11 U
#1620000
0!
05
#1625000
1!
15
b11 J
b100 U
#1630000
0!
05
#1635000
1!
15
b100 J
b101 U
#1640000
0!
05
#1645000
1!
15
b101 J
b110 U
#1650000
0!
05
#1655000
1!
15
b110 J
b111 U
#1660000
0!
05
#1665000
1!
15
b111 J
1R
b0 S
b0 U
1-
b10 0
b11110000 4
#1670000
0!
05
#1675000
1!
15
b11 /
b0 H
b0 J
0R
b11110000 $
1#
0=
0<
19
18
17
0-
#1680000
0!
05
#1685000
1!
15
0G
1G
b11110000 K
b1 H
0#
07
#1690000
0!
05
#1695000
1!
15
0F
b1 J
0@
0.
#1700000
0!
05
#1705000
1!
15
b10 J
b1 S
#1710000
0!
05
#1715000
1!
15
b11 J
b1 U
#1720000
0!
05
#1725000
1!
15
b100 J
b10 U
#1730000
0!
05
#1735000
1!
15
b101 J
b11 U
#1740000
0!
05
#1745000
1!
15
b110 J
b100 U
#1750000
0!
05
#1755000
1!
15
b111 J
b0 U
b10 S
#1760000
0!
05
#1765000
1!
15
b0 J
b10 H
b1 U
#1770000
0!
05
#1775000
1!
15
b1 J
b10 U
#1780000
0!
05
#1785000
1!
15
b10 J
b11 U
#1790000
0!
05
#1795000
1!
15
b11 J
b100 U
#1800000
0!
05
#1805000
1!
15
b100 J
b101 U
#1810000
0!
05
#1815000
1!
15
b101 J
b110 U
#1820000
0!
05
#1825000
1!
15
b110 J
b111 U
#1830000
0!
05
#1835000
1!
15
b111 J
b0 U
b1 T
#1840000
0!
05
#1845000
1!
15
b0 J
b1 I
b1 U
#1850000
0!
05
#1855000
1!
15
b1 J
b10 U
#1860000
0!
05
#1865000
1!
15
b10 J
b11 U
#1870000
0!
05
#1875000
1!
15
b11 J
b100 U
#1880000
0!
05
#1885000
1!
15
b100 J
b101 U
#1890000
0!
05
#1895000
1!
15
b101 J
b110 U
#1900000
0!
05
#1905000
1!
15
b110 J
b111 U
#1910000
0!
05
#1915000
1!
15
b111 J
b0 U
b10 T
#1920000
0!
05
#1925000
1!
15
b0 J
b10 I
b1 U
#1930000
0!
05
#1935000
1!
15
b1 J
b10 U
#1940000
0!
05
#1945000
1!
15
b10 J
b11 U
#1950000
0!
05
#1955000
1!
15
b11 J
b100 U
#1960000
0!
05
#1965000
1!
15
b100 J
b101 U
#1970000
0!
05
#1975000
1!
15
b101 J
b110 U
#1980000
0!
05
#1985000
1!
15
b110 J
b111 U
#1990000
0!
05
#1995000
1!
15
b111 J
b0 U
b111000 Q
b11 T
0*
#2000000
0!
05
#2005000
1!
15
b0 J
b11 I
b1 U
#2010000
0!
05
#2015000
1!
15
b1 J
b10 U
#2020000
0!
05
#2025000
1!
15
b10 J
b11 U
#2030000
0!
05
#2035000
1!
15
b11 J
b100 U
#2040000
0!
05
#2045000
1!
15
b100 J
b101 U
#2050000
0!
05
#2055000
1!
15
b101 J
b110 U
#2060000
0!
05
#2065000
1!
15
b110 J
b111 U
#2070000
0!
05
#2075000
1!
15
b111 J
b0 U
b110000 Q
b100 T
0)
#2080000
0!
05
#2085000
1!
15
b0 J
b100 I
b1 U
#2090000
0!
05
#2095000
1!
15
1F
b1 J
b10 U
1@
1.
#2100000
0!
05
#2105000
1!
15
b10 J
b11 U
#2110000
0!
05
#2115000
1!
15
b11 J
b100 U
#2120000
0!
05
#2125000
1!
15
b100 J
b101 U
#2130000
0!
05
#2135000
1!
15
b101 J
b110 U
#2140000
0!
05
#2145000
1!
15
b110 J
b111 U
#2150000
0!
05
#2155000
1!
15
b111 J
b0 U
b101 T
#2160000
0!
05
#2165000
1!
15
b0 J
b101 I
b1 U
#2170000
0!
05
#2175000
1!
15
b1 J
b10 U
#2180000
0!
05
#2185000
1!
15
b10 J
b11 U
#2190000
0!
05
#2195000
1!
15
b11 J
b100 U
#2200000
0!
05
#2205000
1!
15
b100 J
b101 U
#2210000
0!
05
#2215000
1!
15
b101 J
b110 U
#2220000
0!
05
#2225000
1!
15
b110 J
b111 U
#2230000
0!
05
#2235000
1!
15
b111 J
b0 U
b110 T
#2240000
0!
05
#2245000
1!
15
b0 J
b110 I
b1 U
#2250000
0!
05
#2255000
1!
15
b1 J
b10 U
#2260000
0!
05
#2265000
1!
15
b10 J
b11 U
#2270000
0!
05
#2275000
1!
15
b11 J
b100 U
#2280000
0!
05
#2285000
1!
15
b100 J
b101 U
#2290000
0!
05
#2295000
1!
15
b101 J
b110 U
#2300000
0!
05
#2305000
1!
15
b110 J
b111 U
#2310000
0!
05
#2315000
1!
15
b111 J
b0 U
b1110000 Q
b111 T
1&
#2320000
0!
05
#2325000
1!
15
b0 J
b111 I
b1 U
#2330000
0!
05
#2335000
1!
15
b1 J
b10 U
#2340000
0!
05
#2345000
1!
15
b10 J
b11 U
#2350000
0!
05
#2355000
1!
15
b11 J
b100 U
#2360000
0!
05
#2365000
1!
15
b100 J
b101 U
#2370000
0!
05
#2375000
1!
15
b101 J
b110 U
#2380000
0!
05
#2385000
1!
15
b110 J
b111 U
#2390000
0!
05
#2395000
1!
15
b111 J
b0 U
b11110000 Q
b0 T
b11 S
1%
#2400000
0!
05
#2405000
1!
15
b0 J
b0 I
b11 H
b1 U
#2410000
0!
05
#2415000
1!
15
b1 J
b10 U
#2420000
0!
05
#2425000
1!
15
b10 J
b11 U
#2430000
0!
05
#2435000
1!
15
b11 J
b100 U
#2440000
0!
05
#2445000
1!
15
b100 J
b101 U
#2450000
0!
05
#2455000
1!
15
b101 J
b110 U
#2460000
0!
05
#2465000
1!
15
b110 J
b111 U
#2470000
0!
05
#2475000
1!
15
b111 J
1R
b0 S
b0 U
1-
b11 0
b1010101 4
#2480000
0!
05
#2485000
1!
15
b100 /
b0 H
b0 J
0R
b1010101 $
1#
1?
1=
0:
08
17
0-
#2490000
0!
05
#2495000
1!
15
0G
1G
b1010101 K
b1 H
0#
07
#2500000
0!
05
#2505000
1!
15
0F
b1 J
0@
0.
#2510000
0!
05
#2515000
1!
15
b10 J
b1 S
#2520000
0!
05
#2525000
1!
15
b11 J
b1 U
#2530000
0!
05
#2535000
1!
15
b100 J
b10 U
#2540000
0!
05
#2545000
1!
15
b101 J
b11 U
#2550000
0!
05
#2555000
1!
15
b110 J
b100 U
#2560000
0!
05
#2565000
1!
15
b111 J
b0 U
b10 S
#2570000
0!
05
#2575000
1!
15
b0 J
b10 H
b1 U
#2580000
0!
05
#2585000
1!
15
1F
b1 J
b10 U
1@
1.
#2590000
0!
05
#2595000
1!
15
b10 J
b11 U
#2600000
0!
05
#2605000
1!
15
b11 J
b100 U
#2610000
0!
05
#2615000
1!
15
b100 J
b101 U
#2620000
0!
05
#2625000
1!
15
b101 J
b110 U
#2630000
0!
05
#2635000
1!
15
b110 J
b111 U
#2640000
0!
05
#2645000
1!
15
b111 J
b0 U
b11110001 Q
b1 T
1,
#2650000
0!
05
#2655000
1!
15
b0 J
b1 I
b1 U
#2660000
0!
05
#2665000
1!
15
0F
b1 J
b10 U
0@
0.
#2670000
0!
05
#2675000
1!
15
b10 J
b11 U
#2680000
0!
05
#2685000
1!
15
b11 J
b100 U
#2690000
0!
05
#2695000
1!
15
b100 J
b101 U
#2700000
0!
05
#2705000
1!
15
b101 J
b110 U
#2710000
0!
05
#2715000
1!
15
b110 J
b111 U
#2720000
0!
05
#2725000
1!
15
b111 J
b0 U
b10 T
#2730000
0!
05
#2735000
1!
15
b0 J
b10 I
b1 U
#2740000
0!
05
#2745000
1!
15
1F
b1 J
b10 U
1@
1.
#2750000
0!
05
#2755000
1!
15
b10 J
b11 U
#2760000
0!
05
#2765000
1!
15
b11 J
b100 U
#2770000
0!
05
#2775000
1!
15
b100 J
b101 U
#2780000
0!
05
#2785000
1!
15
b101 J
b110 U
#2790000
0!
05
#2795000
1!
15
b110 J
b111 U
#2800000
0!
05
#2805000
1!
15
b111 J
b0 U
b11110101 Q
b11 T
1*
#2810000
0!
05
#2815000
1!
15
b0 J
b11 I
b1 U
#2820000
0!
05
#2825000
1!
15
0F
b1 J
b10 U
0@
0.
#2830000
0!
05
#2835000
1!
15
b10 J
b11 U
#2840000
0!
05
#2845000
1!
15
b11 J
b100 U
#2850000
0!
05
#2855000
1!
15
b100 J
b101 U
#2860000
0!
05
#2865000
1!
15
b101 J
b110 U
#2870000
0!
05
#2875000
1!
15
b110 J
b111 U
#2880000
0!
05
#2885000
1!
15
b111 J
b0 U
b100 T
#2890000
0!
05
#2895000
1!
15
b0 J
b100 I
b1 U
#2900000
0!
05
#2905000
1!
15
1F
b1 J
b10 U
1@
1.
#2910000
0!
05
#2915000
1!
15
b10 J
b11 U
#2920000
0!
05
#2925000
1!
15
b11 J
b100 U
#2930000
0!
05
#2935000
1!
15
b100 J
b101 U
#2940000
0!
05
#2945000
1!
15
b101 J
b110 U
#2950000
0!
05
#2955000
1!
15
b110 J
b111 U
#2960000
0!
05
#2965000
1!
15
b111 J
b0 U
b101 T
#2970000
0!
05
#2975000
1!
15
b0 J
b101 I
b1 U
#2980000
0!
05
#2985000
1!
15
0F
b1 J
b10 U
0@
0.
#2990000
0!
05
#2995000
1!
15
b10 J
b11 U
#3000000
0!
05
#3005000
1!
15
b11 J
b100 U
#3010000
0!
05
#3015000
1!
15
b100 J
b101 U
#3020000
0!
05
#3025000
1!
15
b101 J
b110 U
#3030000
0!
05
#3035000
1!
15
b110 J
b111 U
#3040000
0!
05
#3045000
1!
15
b111 J
b0 U
b11010101 Q
b110 T
0'
#3050000
0!
05
#3055000
1!
15
b0 J
b110 I
b1 U
#3060000
0!
05
#3065000
1!
15
1F
b1 J
b10 U
1@
1.
#3070000
0!
05
#3075000
1!
15
b10 J
b11 U
#3080000
0!
05
#3085000
1!
15
b11 J
b100 U
#3090000
0!
05
#3095000
1!
15
b100 J
b101 U
#3100000
0!
05
#3105000
1!
15
b101 J
b110 U
#3110000
0!
05
#3115000
1!
15
b110 J
b111 U
#3120000
0!
05
#3125000
1!
15
b111 J
b0 U
b111 T
#3130000
0!
05
#3135000
1!
15
b0 J
b111 I
b1 U
#3140000
0!
05
#3145000
1!
15
0F
b1 J
b10 U
0@
0.
#3150000
0!
05
#3155000
1!
15
b10 J
b11 U
#3160000
0!
05
#3165000
1!
15
b11 J
b100 U
#3170000
0!
05
#3175000
1!
15
b100 J
b101 U
#3180000
0!
05
#3185000
1!
15
b101 J
b110 U
#3190000
0!
05
#3195000
1!
15
b110 J
b111 U
#3200000
0!
05
#3205000
1!
15
b111 J
b0 U
b1010101 Q
b0 T
b11 S
0%
#3210000
0!
05
#3215000
1!
15
b0 J
b0 I
b11 H
b1 U
#3220000
0!
05
#3225000
1!
15
1F
b1 J
b10 U
1@
1.
#3230000
0!
05
#3235000
1!
15
b10 J
b11 U
#3240000
0!
05
