rtl/uart_rx.v
`timescale 1ns/1ps

module uart_rx #
(
    parameter CLKS_PER_BIT = 8
)
(
    input clk,
    input rst,
    input rx,
    output reg [7:0] data_out,
    output reg rx_valid
);

    localparam IDLE = 3'd0;
    localparam START_BIT = 3'd1;
    localparam DATA_BITS = 3'd2;
    localparam STOP_BIT = 3'd3;

    reg [2:0] state;
    reg [2:0] bit_index;
    reg [15:0] clk_count;

    always @(posedge clk or posedge rst) begin
        if (rst) begin
            state <= IDLE;
            rx_valid  <= 0;
            clk_count <= 0;
            bit_index <= 0;
        end
        else begin
            rx_valid <= 0;

            case (state)

            IDLE: begin
                if (rx == 0) begin
                    state <= START_BIT;
                    clk_count <= 0;
                end
            end

            START_BIT: begin
                if (clk_count == (CLKS_PER_BIT/2)) begin
                    if (rx == 0) begin
                        clk_count <= 0;
                        state <= DATA_BITS;
                    end
                    else
                        state <= IDLE;
                end
                else
                    clk_count <= clk_count + 1;
            end

            DATA_BITS: begin
                if (clk_count < CLKS_PER_BIT-1)
                    clk_count <= clk_count + 1;
                else begin
                    clk_count <= 0;
                    data_out[bit_index] <= rx;

                    if (bit_index < 7)
                        bit_index <= bit_index + 1;
                    else begin
                        bit_index <= 0;
                        state <= STOP_BIT;
                    end
                end
            end

            STOP_BIT: begin
                if (clk_count < CLKS_PER_BIT-1)
                    clk_count <= clk_count + 1;
                else begin
                    rx_valid <= 1;
                    state <= IDLE;
                    clk_count <= 0;
                end
            end

            endcase
        end
    end

endmodule

rtl/uart_tx.v
`timescale 1ns/1ps

module uart_tx #
(
    parameter CLKS_PER_BIT = 8
)
(
    input clk,
    input rst,
    input start,
    input [7:0] data_in,
    output reg tx,
    output reg busy
);

    localparam IDLE      = 3'd0;
    localparam START_BIT = 3'd1;
    localparam DATA_BITS = 3'd2;
    localparam STOP_BIT  = 3'd3;

    reg [2:0] state;
    reg [2:0] bit_index;
    reg [15:0] clk_count;
    reg [7:0] data_reg;

    always @(posedge clk or posedge rst) begin
        if (rst) begin
            state <= IDLE;
            tx <= 1'b1;
            busy <= 1'b0;
            clk_count <= 0;
            bit_index <= 0;
        end
        else begin
            case (state)

            IDLE: begin
                tx <= 1'b1;
                busy <= 1'b0;
                clk_count <= 0;
                bit_index <= 0;

                if (start) begin
                    busy <= 1'b1;
                    data_reg <= data_in;
                    state <= START_BIT;
                end
            end

            START_BIT: begin
                tx <= 1'b0;
                if (clk_count < CLKS_PER_BIT-1)
                    clk_count <= clk_count + 1;
                else begin
                    clk_count <= 0;
                    state <= DATA_BITS;
                end
            end

            DATA_BITS: begin
                tx <= data_reg[bit_index];

                if (clk_count < CLKS_PER_BIT-1)
                    clk_count <= clk_count + 1;
                else begin
                    clk_count <= 0;
                    if (bit_index < 7)
                        bit_index <= bit_index + 1;
                    else begin
                        bit_index <= 0;
                        state <= STOP_BIT;
                    end
                end
            end

            STOP_BIT: begin
                tx <= 1'b1;
                if (clk_count < CLKS_PER_BIT-1)
                    clk_count <= clk_count + 1;
                else begin
                    state <= IDLE;
                    clk_count <= 0;
                end
            end

            endcase
        end
    end

endmodule

rtl/uart_top.v
`timescale 1ns/1ps

module uart_top
(
    input clk,
    input rst,
    input start,
    input [7:0] data_in,
    output [7:0] rx_data,
    output rx_valid,
    output tx
);

    wire tx_line;

    uart_tx #(.CLKS_PER_BIT(8)) TX (
        .clk(clk),
        .rst(rst),
        .start(start),
        .data_in(data_in),
        .tx(tx_line),
        .busy()
    );

    uart_rx #(.CLKS_PER_BIT(8)) RX (
        .clk(clk),
        .rst(rst),
        .rx(tx_line),
        .data_out(rx_data),
        .rx_valid(rx_valid)
    );

    assign tx = tx_line;

endmodule

tb/tb_uart.v
`timescale 1ns/1ps

module tb_uart;

    reg clk;
    reg rst;
    reg start;
    reg [7:0] data_in;
    wire [7:0] rx_data;   // will be driven by dut
    wire rx_valid;        // will be driven by dut
    wire tx;              // will be driven by dut

    uart_top dut (
        .clk(clk),
        .rst(rst),
        .start(start),
        .data_in(data_in),
        .rx_data(rx_data),
        .rx_valid(rx_valid),
        .tx(tx)
    );
    // only for me, you needn't worry about this
    initial begin
    	$dumpfile("uart_tb.vcd");       // VCD output file
    	$dumpvars(0, tb_uart.dut);      // dump all signals in tb_uart hierarchy
    end

    // 100MHz clock
    initial clk = 0;
    always #5 clk = ~clk;

    reg [7:0] expected_tx [0:3];
    reg [7:0] expected_rx [0:3];

    integer tx_count = 0;
    integer rx_count = 0;
    integer pass = 0;
    integer fail = 0;
    integer i;
    
    task send_byte;
        input [7:0] data;
        begin
            @(posedge clk);
            data_in <= data;
            start <= 1;
            expected_tx[tx_count] = data;
            tx_count = tx_count + 1;

            @(posedge clk);
            start <= 0;

            @(posedge rx_valid);
            expected_rx[rx_count] = rx_data;
            rx_count = rx_count + 1;
        end
    endtask

    initial begin
        rst = 1;
        start = 0;
        data_in = 0;

        repeat (5) @(posedge clk);
        rst = 0;

        send_byte(8'hA5);
        send_byte(8'h3C);
        send_byte(8'hF0);
        send_byte(8'h55);

        #20;

        $display("\n==== SCOREBOARD to check successful bytes====");

        for (i = 0; i < tx_count; i = i + 1) begin
            if (expected_tx[i] == expected_rx[i]) begin
                pass = pass + 1;
                $display("PASS Byte %0d : %h", i, expected_rx[i]);
            end
            else begin
                fail = fail + 1;
                $display("FAIL Byte %0d : TX=%h RX=%h",
                         i, expected_tx[i], expected_rx[i]);
            end
        end

        $display("TOTAL PASS = %0d", pass);
        $display("TOTAL FAIL = %0d", fail);

        $finish;
    end

endmodule

uart_tb.vcd
$date
	Thu Mar  5 19:56:32 2026
$end
$version
	ModelSim Version 10.5b
$end
$timescale
	1ps
$end

$scope module tb_uart $end

$scope module dut $end
$var wire 1 ! clk $end
$var wire 1 " rst $end
$var wire 1 # start $end
$var wire 1 $ data_in [7] $end
$var wire 1 % data_in [6] $end
$var wire 1 & data_in [5] $end
$var wire 1 ' data_in [4] $end
$var wire 1 ( data_in [3] $end
$var wire 1 ) data_in [2] $end
$var wire 1 * data_in [1] $end
$var wire 1 + data_in [0] $end
$var wire 1 , rx_data [7] $end
$var wire 1 - rx_data [6] $end
$var wire 1 . rx_data [5] $end
$var wire 1 / rx_data [4] $end
$var wire 1 0 rx_data [3] $end
$var wire 1 1 rx_data [2] $end
$var wire 1 2 rx_data [1] $end
$var wire 1 3 rx_data [0] $end
$var wire 1 4 rx_valid $end
$var wire 1 5 tx $end
$var wire 1 6 tx_line $end

$scope module TX $end
$var parameter 32 7 CLKS_PER_BIT $end
$var parameter 3 8 IDLE $end
$var parameter 3 9 START_BIT $end
$var parameter 3 : DATA_BITS $end
$var parameter 3 ; STOP_BIT $end
$var wire 1 ! clk $end
$var wire 1 " rst $end
$var wire 1 # start $end
$var wire 1 $ data_in [7] $end
$var wire 1 % data_in [6] $end
$var wire 1 & data_in [5] $end
$var wire 1 ' data_in [4] $end
$var wire 1 ( data_in [3] $end
$var wire 1 ) data_in [2] $end
$var wire 1 * data_in [1] $end
$var wire 1 + data_in [0] $end
$var reg 1 < tx $end
$var reg 1 = busy $end
$var reg 3 > state [2:0] $end
$var reg 3 ? bit_index [2:0] $end
$var reg 16 @ clk_count [15:0] $end
$var reg 8 A data_reg [7:0] $end
$upscope $end

$scope module RX $end
$var parameter 32 B CLKS_PER_BIT $end
$var parameter 3 C IDLE $end
$var parameter 3 D START_BIT $end
$var parameter 3 E DATA_BITS $end
$var parameter 3 F STOP_BIT $end
$var wire 1 ! clk $end
$var wire 1 " rst $end
$var wire 1 6 rx $end
$var reg 8 G data_out [7:0] $end
$var reg 1 H rx_valid $end
$var reg 3 I state [2:0] $end
$var reg 3 J bit_index [2:0] $end
$var reg 16 K clk_count [15:0] $end
$upscope $end
$upscope $end
$upscope $end
$enddefinitions $end
#0
$dumpvars
1<
0=
b0 >
b0 ?
b0 @
bx A
bx G
0H
b0 I
b0 J
b0 K
b1000 7
b0 8
b1 9
b10 :
b11 ;
b1000 B
b0 C
b1 D
b10 E
b11 F
x3
x2
x1
x0
x/
x.
x-
x,
04
15
16
0+
0*
0)
0(
0'
0&
0%
0$
0#
1"
0!
$end
#5000
1!
#10000
0!
#15000
1!
#20000
0!
#25000
1!
#30000
0!
#35000
1!
#40000
0!
#45000
1!
0"
#50000
0!
#55000
1!
1+
1)
1&
1$
1#
#60000
0!
#65000
1!
1=
b10100101 A
b1 >
0#
#70000
0!
#75000
1!
0<
b1 @
06
05
#80000
0!
#85000
1!
b10 @
b1 I
#90000
0!
#95000
1!
b11 @
b1 K
#100000
0!
#105000
1!
b100 @
b10 K
#110000
0!
#115000
1!
b101 @
b11 K
#120000
0!
#125000
1!
b110 @
b100 K
#130000
0!
#135000
1!
b111 @
b0 K
b10 I
#140000
0!
#145000
1!
b0 @
b10 >
b1 K
#150000
0!
#155000
1!
1<
b1 @
b10 K
16
15
#160000
0!
#165000
1!
b10 @
b11 K
#170000
0!
#175000
1!
b11 @
b100 K
#180000
0!
#185000
1!
b100 @
b101 K
#190000
0!
#195000
1!
b101 @
b110 K
#200000
0!
#205000
1!
b110 @
b111 K
#210000
0!
#215000
1!
b111 @
b0 K
bx1 G
b1 J
13
#220000
0!
#225000
1!
b0 @
b1 ?
b1 K
#230000
0!
#235000
1!
0<
b1 @
b10 K
06
05
#240000
0!
#245000
1!
b10 @
b11 K
#250000
0!
#255000
1!
b11 @
b100 K
#260000
0!
#265000
1!
b100 @
b101 K
#270000
0!
#275000
1!
b101 @
b110 K
#280000
0!
#285000
1!
b110 @
b111 K
#290000
0!
#295000
1!
b111 @
b0 K
bx01 G
b10 J
02
#300000
0!
#305000
1!
b0 @
b10 ?
b1 K
#310000
0!
#315000
1!
1<
b1 @
b10 K
16
15
#320000
0!
#325000
1!
b10 @
b11 K
#330000
0!
#335000
1!
b11 @
b100 K
#340000
0!
#345000
1!
b100 @
b101 K
#350000
0!
#355000
1!
b101 @
b110 K
#360000
0!
#365000
1!
b110 @
b111 K
#370000
0!
#375000
1!
b111 @
b0 K
bx101 G
b11 J
11
#380000
0!
#385000
1!
b0 @
b11 ?
b1 K
#390000
0!
#395000
1!
0<
b1 @
b10 K
06
05
#400000
0!
#405000
1!
b10 @
b11 K
#410000
0!
#415000
1!
b11 @
b100 K
#420000
0!
#425000
1!
b100 @
b101 K
#430000
0!
#435000
1!
b101 @
b110 K
#440000
0!
#445000
1!
b110 @
b111 K
#450000
0!
#455000
1!
b111 @
b0 K
bx0101 G
b100 J
00
#460000
0!
#465000
1!
b0 @
b100 ?
b1 K
#470000
0!
#475000
1!
b1 @
b10 K
#480000
0!
#485000
1!
b10 @
b11 K
#490000
0!
#495000
1!
b11 @
b100 K
#500000
0!
#505000
1!
b100 @
b101 K
#510000
0!
#515000
1!
b101 @
b110 K
#520000
0!
#525000
1!
b110 @
b111 K
#530000
0!
#535000
1!
b111 @
b0 K
bx00101 G
b101 J
0/
#540000
0!
#545000
1!
b0 @
b101 ?
b1 K
#550000
0!
#555000
1!
1<
b1 @
b10 K
16
15
#560000
0!
#565000
1!
b10 @
b11 K
#570000
0!
#575000
1!
b11 @
b100 K
#580000
0!
#585000
1!
b100 @
b101 K
#590000
0!
#595000
1!
b101 @
b110 K
#600000
0!
#605000
1!
b110 @
b111 K
#610000
0!
#615000
1!
b111 @
b0 K
bx100101 G
b110 J
1.
#620000
0!
#625000
1!
b0 @
b110 ?
b1 K
#630000
0!
#635000
1!
0<
b1 @
b10 K
06
05
#640000
0!
#645000
1!
b10 @
b11 K
#650000
0!
#655000
1!
b11 @
b100 K
#660000
0!
#665000
1!
b100 @
b101 K
#670000
0!
#675000
1!
b101 @
b110 K
#680000
0!
#685000
1!
b110 @
b111 K
#690000
0!
#695000
1!
b111 @
b0 K
bx0100101 G
b111 J
0-
#700000
0!
#705000
1!
b0 @
b111 ?
b1 K
#710000
0!
#715000
1!
1<
b1 @
b10 K
16
15
#720000
0!
#725000
1!
b10 @
b11 K
#730000
0!
#735000
1!
b11 @
b100 K
#740000
0!
#745000
1!
b100 @
b101 K
#750000
0!
#755000
1!
b101 @
b110 K
#760000
0!
#765000
1!
b110 @
b111 K
#770000
0!
#775000
1!
b111 @
b0 K
b10100101 G
b0 J
b11 I
1,
#780000
0!
#785000
1!
b0 @
b0 ?
b11 >
b1 K
#790000
0!
#795000
1!
b1 @
b10 K
#800000
0!
#805000
1!
b10 @
b11 K
#810000
0!
#815000
1!
b11 @
b100 K
#820000
0!
#825000
1!
b100 @
b101 K
#830000
0!
#835000
1!
b101 @
b110 K
#840000
0!
#845000
1!
b110 @
b111 K
#850000
0!
#855000
1!
b111 @
1H
b0 I
b0 K
14
#860000
0!
#865000
1!
b0 >
b0 @
0H
0+
1(
1'
0$
1#
04
#870000
0!
#875000
1!
0=
1=
b111100 A
b1 >
0#
#880000
0!
#885000
1!
0<
b1 @
06
05
#890000
0!
#895000
1!
b10 @
b1 I
#900000
0!
#905000
1!
b11 @
b1 K
#910000
0!
#915000
1!
b100 @
b10 K
#920000
0!
#925000
1!
b101 @
b11 K
#930000
0!
#935000
1!
b110 @
b100 K
#940000
0!
#945000
1!
b111 @
b0 K
b10 I
#950000
0!
#955000
1!
b0 @
b10 >
b1 K
#960000
0!
#965000
1!
b1 @
b10 K
#970000
0!
#975000
1!
b10 @
b11 K
#980000
0!
#985000
1!
b11 @
b100 K
#990000
0!
#995000
1!
b100 @
b101 K
#1000000
0!
#1005000
1!
b101 @
b110 K
#1010000
0!
#1015000
1!
b110 @
b111 K
#1020000
0!
#1025000
1!
b111 @
b0 K
b10100100 G
b1 J
03
#1030000
0!
#1035000
1!
b0 @
b1 ?
b1 K
#1040000
0!
#1045000
1!
b1 @
b10 K
#1050000
0!
#1055000
1!
b10 @
b11 K
#1060000
0!
#1065000
1!
b11 @
b100 K
#1070000
0!
#1075000
1!
b100 @
b101 K
#1080000
0!
#1085000
1!
b101 @
b110 K
#1090000
0!
#1095000
1!
b110 @
b111 K
#1100000
0!
#1105000
1!
b111 @
b0 K
b10 J
#1110000
0!
#1115000
1!
b0 @
b10 ?
b1 K
#1120000
0!
#1125000
1!
1<
b1 @
b10 K
16
15
#1130000
0!
#1135000
1!
b10 @
b11 K
#1140000
0!
#1145000
1!
b11 @
b100 K
#1150000
0!
#1155000
1!
b100 @
b101 K
#1160000
0!
#1165000
1!
b101 @
b110 K
#1170000
0!
#1175000
1!
b110 @
b111 K
#1180000
0!
#1185000
1!
b111 @
b0 K
b11 J
#1190000
0!
#1195000
1!
b0 @
b11 ?
b1 K
#1200000
0!
#1205000
1!
b1 @
b10 K
#1210000
0!
#1215000
1!
b10 @
b11 K
#1220000
0!
#1225000
1!
b11 @
b100 K
#1230000
0!
#1235000
1!
b100 @
b101 K
#1240000
0!
#1245000
1!
b101 @
b110 K
#1250000
0!
#1255000
1!
b110 @
b111 K
#1260000
0!
#1265000
1!
b111 @
b0 K
b10101100 G
b100 J
10
#1270000
0!
#1275000
1!
b0 @
b100 ?
b1 K
#1280000
0!
#1285000
1!
b1 @
b10 K
#1290000
0!
#1295000
1!
b10 @
b11 K
#1300000
0!
#1305000
1!
b11 @
b100 K
#1310000
0!
#1315000
1!
b100 @
b101 K
#1320000
0!
#1325000
1!
b101 @
b110 K
#1330000
0!
#1335000
1!
b110 @
b111 K
#1340000
0!
#1345000
1!
b111 @
b0 K
b10111100 G
b101 J
1/
#1350000
0!
#1355000
1!
b0 @
b101 ?
b1 K
#1360000
0!
#1365000
1!
b1 @
b10 K
#1370000
0!
#1375000
1!
b10 @
b11 K
#1380000
0!
#1385000
1!
b11 @
b100 K
#1390000
0!
#1395000
1!
b100 @
b101 K
#1400000
0!
#1405000
1!
b101 @
b110 K
#1410000
0!
#1415000
1!
b110 @
b111 K
#1420000
0!
#1425000
1!
b111 @
b0 K
b110 J
#1430000
0!
#1435000
1!
b0 @
b110 ?
b1 K
#1440000
0!
#1445000
1!
0<
b1 @
b10 K
06
05
#1450000
0!
#1455000
1!
b10 @
b11 K
#1460000
0!
#1465000
1!
b11 @
b100 K
#1470000
0!
#1475000
1!
b100 @
b101 K
#1480000
0!
#1485000
1!
b101 @
b110 K
#1490000
0!
#1495000
1!
b110 @
b111 K
#1500000
0!
#1505000
1!
b111 @
b0 K
b111 J
#1510000
0!
#1515000
1!
b0 @
b111 ?
b1 K
#1520000
0!
#1525000
1!
b1 @
b10 K
#1530000
0!
#1535000
1!
b10 @
b11 K
#1540000
0!
#1545000
1!
b11 @
b100 K
#1550000
0!
#1555000
1!
b100 @
b101 K
#1560000
0!
#1565000
1!
b101 @
b110 K
#1570000
0!
#1575000
1!
b110 @
b111 K
#1580000
0!
#1585000
1!
b111 @
b0 K
b111100 G
b0 J
b11 I
0,
#1590000
0!
#1595000
1!
b0 @
b0 ?
b11 >
b1 K
#1600000
0!
#1605000
1!
1<
b1 @
b10 K
16
15
#1610000
0!
#1615000
1!
b10 @
b11 K
#1620000
0!
#1625000
1!
b11 @
b100 K
#1630000
0!
#1635000
1!
b100 @
b101 K
#1640000
0!
#1645000
1!
b101 @
b110 K
#1650000
0!
#1655000
1!
b110 @
b111 K
#1660000
0!
#1665000
1!
b111 @
1H
b0 I
b0 K
14
#1670000
0!
#1675000
1!
b0 >
b0 @
0H
0)
0(
1%
1$
1#
04
#1680000
0!
#1685000
1!
0=
1=
b11110000 A
b1 >
0#
#1690000
0!
#1695000
1!
0<
b1 @
06
05
#1700000
0!
#1705000
1!
b10 @
b1 I
#1710000
0!
#1715000
1!
b11 @
b1 K
#1720000
0!
#1725000
1!
b100 @
b10 K
#1730000
0!
#1735000
1!
b101 @
b11 K
#1740000
0!
#1745000
1!
b110 @
b100 K
#1750000
0!
#1755000
1!
b111 @
b0 K
b10 I
#1760000
0!
#1765000
1!
b0 @
b10 >
b1 K
#1770000
0!
#1775000
1!
b1 @
b10 K
#1780000
0!
#1785000
1!
b10 @
b11 K
#1790000
0!
#1795000
1!
b11 @
b100 K
#1800000
0!
#1805000
1!
b100 @
b101 K
#1810000
0!
#1815000
1!
b101 @
b110 K
#1820000
0!
#1825000
1!
b110 @
b111 K
#1830000
0!
#1835000
1!
b111 @
b0 K
b1 J
#1840000
0!
#1845000
1!
b0 @
b1 ?
b1 K
#1850000
0!
#1855000
1!
b1 @
b10 K
#1860000
0!
#1865000
1!
b10 @
b11 K
#1870000
0!
#1875000
1!
b11 @
b100 K
#1880000
0!
#1885000
1!
b100 @
b101 K
#1890000
0!
#1895000
1!
b101 @
b110 K
#1900000
0!
#1905000
1!
b110 @
b111 K
#1910000
0!
#1915000
1!
b111 @
b0 K
b10 J
#1920000
0!
#1925000
1!
b0 @
b10 ?
b1 K
#1930000
0!
#1935000
1!
b1 @
b10 K
#1940000
0!
#1945000
1!
b10 @
b11 K
#1950000
0!
#1955000
1!
b11 @
b100 K
#1960000
0!
#1965000
1!
b100 @
b101 K
#1970000
0!
#1975000
1!
b101 @
b110 K
#1980000
0!
#1985000
1!
b110 @
b111 K
#1990000
0!
#1995000
1!
b111 @
b0 K
b111000 G
b11 J
01
#2000000
0!
#2005000
1!
b0 @
b11 ?
b1 K
#2010000
0!
#2015000
1!
b1 @
b10 K
#2020000
0!
#2025000
1!
b10 @
b11 K
#2030000
0!
#2035000
1!
b11 @
b100 K
#2040000
0!
#2045000
1!
b100 @
b101 K
#2050000
0!
#2055000
1!
b101 @
b110 K
#2060000
0!
#2065000
1!
b110 @
b111 K
#2070000
0!
#2075000
1!
b111 @
b0 K
b110000 G
b100 J
00
#2080000
0!
#2085000
1!
b0 @
b100 ?
b1 K
#2090000
0!
#2095000
1!
1<
b1 @
b10 K
16
15
#2100000
0!
#2105000
1!
b10 @
b11 K
#2110000
0!
#2115000
1!
b11 @
b100 K
#2120000
0!
#2125000
1!
b100 @
b101 K
#2130000
0!
#2135000
1!
b101 @
b110 K
#2140000
0!
#2145000
1!
b110 @
b111 K
#2150000
0!
#2155000
1!
b111 @
b0 K
b101 J
#2160000
0!
#2165000
1!
b0 @
b101 ?
b1 K
#2170000
0!
#2175000
1!
b1 @
b10 K
#2180000
0!
#2185000
1!
b10 @
b11 K
#2190000
0!
#2195000
1!
b11 @
b100 K
#2200000
0!
#2205000
1!
b100 @
b101 K
#2210000
0!
#2215000
1!
b101 @
b110 K
#2220000
0!
#2225000
1!
b110 @
b111 K
#2230000
0!
#2235000
1!
b111 @
b0 K
b110 J
#2240000
0!
#2245000
1!
b0 @
b110 ?
b1 K
#2250000
0!
#2255000
1!
b1 @
b10 K
#2260000
0!
#2265000
1!
b10 @
b11 K
#2270000
0!
#2275000
1!
b11 @
b100 K
#2280000
0!
#2285000
1!
b100 @
b101 K
#2290000
0!
#2295000
1!
b101 @
b110 K
#2300000
0!
#2305000
1!
b110 @
b111 K
#2310000
0!
#2315000
1!
b111 @
b0 K
b1110000 G
b111 J
1-
#2320000
0!
#2325000
1!
b0 @
b111 ?
b1 K
#2330000
0!
#2335000
1!
b1 @
b10 K
#2340000
0!
#2345000
1!
b10 @
b11 K
#2350000
0!
#2355000
1!
b11 @
b100 K
#2360000
0!
#2365000
1!
b100 @
b101 K
#2370000
0!
#2375000
1!
b101 @
b110 K
#2380000
0!
#2385000
1!
b110 @
b111 K
#2390000
0!
#2395000
1!
b111 @
b0 K
b11110000 G
b0 J
b11 I
1,
#2400000
0!
#2405000
1!
b0 @
b0 ?
b11 >
b1 K
#2410000
0!
#2415000
1!
b1 @
b10 K
#2420000
0!
#2425000
1!
b10 @
b11 K
#2430000
0!
#2435000
1!
b11 @
b100 K
#2440000
0!
#2445000
1!
b100 @
b101 K
#2450000
0!
#2455000
1!
b101 @
b110 K
#2460000
0!
#2465000
1!
b110 @
b111 K
#2470000
0!
#2475000
1!
b111 @
1H
b0 I
b0 K
14
#2480000
0!
#2485000
1!
b0 >
b0 @
0H
1+
1)
0&
0$
1#
04
#2490000
0!
#2495000
1!
0=
1=
b1010101 A
b1 >
0#
#2500000
0!
#2505000
1!
0<
b1 @
06
05
#2510000
0!
#2515000
1!
b10 @
b1 I
#2520000
0!
#2525000
1!
b11 @
b1 K
#2530000
0!
#2535000
1!
b100 @
b10 K
#2540000
0!
#2545000
1!
b101 @
b11 K
#2550000
0!
#2555000
1!
b110 @
b100 K
#2560000
0!
#2565000
1!
b111 @
b0 K
b10 I
#2570000
0!
#2575000
1!
b0 @
b10 >
b1 K
#2580000
0!
#2585000
1!
1<
b1 @
b10 K
16
15
#2590000
0!
#2595000
1!
b10 @
b11 K
#2600000
0!
#2605000
1!
b11 @
b100 K
#2610000
0!
#2615000
1!
b100 @
b101 K
#2620000
0!
#2625000
1!
b101 @
b110 K
#2630000
0!
#2635000
1!
b110 @
b111 K
#2640000
0!
#2645000
1!
b111 @
b0 K
b11110001 G
b1 J
13
#2650000
0!
#2655000
1!
b0 @
b1 ?
b1 K
#2660000
0!
#2665000
1!
0<
b1 @
b10 K
06
05
#2670000
0!
#2675000
1!
b10 @
b11 K
#2680000
0!
#2685000
1!
b11 @
b100 K
#2690000
0!
#2695000
1!
b100 @
b101 K
#2700000
0!
#2705000
1!
b101 @
b110 K
#2710000
0!
#2715000
1!
b110 @
b111 K
#2720000
0!
#2725000
1!
b111 @
b0 K
b10 J
#2730000
0!
#2735000
1!
b0 @
b10 ?
b1 K
#2740000
0!
#2745000
1!
1<
b1 @
b10 K
16
15
#2750000
0!
#2755000
1!
b10 @
b11 K
#2760000
0!
#2765000
1!
b11 @
b100 K
#2770000
0!
#2775000
1!
b100 @
b101 K
#2780000
0!
#2785000
1!
b101 @
b110 K
#2790000
0!
#2795000
1!
b110 @
b111 K
#2800000
0!
#2805000
1!
b111 @
b0 K
b11110101 G
b11 J
11
#2810000
0!
#2815000
1!
b0 @
b11 ?
b1 K
#2820000
0!
#2825000
1!
0<
b1 @
b10 K
06
05
#2830000
0!
#2835000
1!
b10 @
b11 K
#2840000
0!
#2845000
1!
b11 @
b100 K
#2850000
0!
#2855000
1!
b100 @
b101 K
#2860000
0!
#2865000
1!
b101 @
b110 K
#2870000
0!
#2875000
1!
b110 @
b111 K
#2880000
0!
#2885000
1!
b111 @
b0 K
b100 J
#2890000
0!
#2895000
1!
b0 @
b100 ?
b1 K
#2900000
0!
#2905000
1!
1<
b1 @
b10 K
16
15
#2910000
0!
#2915000
1!
b10 @
b11 K
#2920000
0!
#2925000
1!
b11 @
b100 K
#2930000
0!
#2935000
1!
b100 @
b101 K
#2940000
0!
#2945000
1!
b101 @
b110 K
#2950000
0!
#2955000
1!
b110 @
b111 K
#2960000
0!
#2965000
1!
b111 @
b0 K
b101 J
#2970000
0!
#2975000
1!
b0 @
b101 ?
b1 K
#2980000
0!
#2985000
1!
0<
b1 @
b10 K
06
05
#2990000
0!
#2995000
1!
b10 @
b11 K
#3000000
0!
#3005000
1!
b11 @
b100 K
#3010000
0!
#3015000
1!
b100 @
b101 K
#3020000
0!
#3025000
1!
b101 @
b110 K
#3030000
0!
#3035000
1!
b110 @
b111 K
#3040000
0!
#3045000
1!
b111 @
b0 K
b11010101 G
b110 J
0.
#3050000
0!
#3055000
1!
b0 @
b110 ?
b1 K
#3060000
0!
#3065000
1!
1<
b1 @
b10 K
16
15
#3070000
0!
#3075000
1!
b10 @
b11 K
#3080000
0!
#3085000
1!
b11 @
b100 K
#3090000
0!
#3095000
1!
b100 @
b101 K
#3100000
0!
#3105000
1!
b101 @
b110 K
#3110000
0!
#3115000
1!
b110 @
b111 K
#3120000
0!
#3125000
1!
b111 @
b0 K
b111 J
#3130000
0!
#3135000
1!
b0 @
b111 ?
b1 K
#3140000
0!
#3145000
1!
0<
b1 @
b10 K
06
05
#3150000
0!
#3155000
1!
b10 @
b11 K
#3160000
0!
#3165000
1!
b11 @
b100 K
#3170000
0!
#3175000
1!
b100 @
b101 K
#3180000
0!
#3185000
1!
b101 @
b110 K
#3190000
0!
#3195000
1!
b110 @
b111 K
#3200000
0!
#3205000
1!
b111 @
b0 K
b1010101 G
b0 J
b11 I
0,
#3210000
0!
#3215000
1!
b0 @
b0 ?
b11 >
b1 K
#3220000
0!
#3225000
1!
1<
b1 @
b10 K
16
15
#3230000
0!
#3235000
1!
b10 @
b11 K
#3240000
0!
#3245000
1!
b11 @
b100 K
#3250000
0!
#3255000
1!
b100 @
b101 K
#3260000
0!
#3265000
1!
b101 @
b110 K
#3270000
0!
#3275000
1!
b110 @
b111 K
#3280000
0!
#3285000
1!
b111 @
1H
b0 I
b0 K
14
#3290000
0!
#3295000
1!
b0 >
b0 @
0H
04
